spyctral/__init__.py
spyctral/core/__init__.py
spyctral/core/core.py
spyctral/core/plot.py
spyctral/io/__init__.py
spyctral/io/fisa.py
spyctral/io/starlight.py
spyctral/utils/__init__.py
spyctral/utils/bunch.py
spyctral_tools-0.0.1rc0.dist-info/LICENSE
spyctral_tools-0.0.1rc0.dist-info/METADATA
spyctral_tools-0.0.1rc0.dist-info/WHEEL
spyctral_tools-0.0.1rc0.dist-info/top_level.txt
spyctral_tools-0.0.1rc0.dist-info/RECORD
