Metadata-Version: 2.2
Name: spyctral-tools
Version: 0.0.1rc0
Summary: Implementation of astronomical objects spectral analisys
Author-email: "Tapia Reina et al." <martina.tapia@mi.unc.edu.ar>
License: The MIT License
Project-URL: Homepage, https://github.com/candelac/Spyctral
Keywords: spyctral,spectra,spectral-synthesis,template-fitting
Classifier: Development Status :: 2 - Pre-Alpha
Classifier: Intended Audience :: Education
Classifier: Intended Audience :: Science/Research
Classifier: License :: OSI Approved :: MIT License
Classifier: Operating System :: OS Independent
Classifier: Programming Language :: Python
Classifier: Programming Language :: Python :: 3.9
Classifier: Programming Language :: Python :: 3.10
Classifier: Programming Language :: Python :: 3.11
Classifier: Programming Language :: Python :: 3.12
Classifier: Programming Language :: Python :: 3.13
Classifier: Topic :: Scientific/Engineering
License-File: LICENSE
Requires-Dist: attrs
Requires-Dist: numpy
Requires-Dist: python-dateutil
Requires-Dist: astropy
Requires-Dist: pandas
Requires-Dist: specutils
Requires-Dist: matplotlib
